[
    {
        "category": "Small",
        "color": "Silver",
        "name": "SPARK PLUG",
        "brand": "Audi",
        "pictures": {
            "img1": "https://i.ibb.co/0GxqwS7/Automobile-Parts-Lfr5aix-11-4469-Iridium-IX-Auto-Car-Spark-Plugs.jpg",
            "img2": "https://i.ibb.co/jfT91NT/2.jpg",
            "img3": "https://i.ibb.co/mRvg6P0/3.webp",
            "img4": "https://i.ibb.co/12hstgx/4.jpg"
        },
        "description": "Lorem ipsum dolor sit amet consectetur, adipisicing elit. Ex molestias iure eaque vero expedita consequuntur accusamus, perferendis fugit, ut ratione blanditiis veritatis aut, temporibus esse doloremque dicta? Corporis odio fuga est veritatis dignissimos obcaecati? Iusto autem praesentium earum quasi ipsa pariatur laboriosam, temporibus quas incidunt? Sed labore repellendus necessitatibus dolore?",
        "quantity": 0,
        "minOrder": 2,
        "price": 22000,
        "shipping": 80,
        "avaiableQuentty": 350,
        "rating": 3.5,
        "review": "Avarage good with value and quality",
        "status": "Hot",
        "offer": "",
        "tag": "Car",
        "stock": "available"
    },
    {
        "category": "Medium",
        "color": "White",
        "name": "BATTERY",
        "brand": "Toyota",
        "pictures": {
            "img1": "https://i.ibb.co/rM2LFbv/istockphoto-899016436-612x612.jpg",
            "img2": "https://i.ibb.co/jfT91NT/2.jpg",
            "img3": "https://i.ibb.co/mRvg6P0/3.webp",
            "img4": "https://i.ibb.co/12hstgx/4.jpg"
        },
        "description": "Lorem ipsum dolor sit amet consectetur, adipisicing elit. Ex molestias iure eaque vero expedita consequuntur accusamus, perferendis fugit, ut ratione blanditiis veritatis aut, temporibus esse doloremque dicta? Corporis odio fuga est veritatis dignissimos obcaecati? Iusto autem praesentium earum quasi ipsa pariatur laboriosam, temporibus quas incidunt? Sed labore repellendus necessitatibus dolore?",
        "quantity": 0,
        "minOrder": 2,
        "price": 20000,
        "shipping": 80,
        "avaiableQuentty": 350,
        "rating": 4,
        "review": "Avarage good with value and quality",
        "status": "",
        "offer": "",
        "tag": "Truck",
        "stock": "available"
    },
    {
        "category": "Large",
        "color": "Black",
        "name": "EXHAUST PIPE",
        "brand": "BMW",
        "pictures": {
            "img1": "https://i.ibb.co/wJ5LSDW/157783049-max.jpg",
            "img2": "https://i.ibb.co/jfT91NT/2.jpg",
            "img3": "https://i.ibb.co/mRvg6P0/3.webp",
            "img4": "https://i.ibb.co/12hstgx/4.jpg"
        },
        "description": "Lorem ipsum dolor sit amet consectetur, adipisicing elit. Ex molestias iure eaque vero expedita consequuntur accusamus, perferendis fugit, ut ratione blanditiis veritatis aut, temporibus esse doloremque dicta? Corporis odio fuga est veritatis dignissimos obcaecati? Iusto autem praesentium earum quasi ipsa pariatur laboriosam, temporibus quas incidunt? Sed labore repellendus necessitatibus dolore?",
        "quantity": 0,
        "minOrder": 2,
        "price": 23000,
        "shipping": 80,
        "avaiableQuentty": 350,
        "rating": 4,
        "review": "Avarage good with value and quality",
        "status": "New",
        "offer": "70",
        "tag": "Car",
        "stock": "out"
    },
    {
        "category": "Extra-Large",
        "color": "Blue",
        "name": "WINDSHIELD",
        "brand": "Bugati",
        "pictures": {
            "img1": "https://i.ibb.co/MftdK5q/automotive-car-glass-500x500.jpg",
            "img2": "https://i.ibb.co/jfT91NT/2.jpg",
            "img3": "https://i.ibb.co/mRvg6P0/3.webp",
            "img4": "https://i.ibb.co/12hstgx/4.jpg"
        },
        "description": "Lorem ipsum dolor sit amet consectetur, adipisicing elit. Ex molestias iure eaque vero expedita consequuntur accusamus, perferendis fugit, ut ratione blanditiis veritatis aut, temporibus esse doloremque dicta? Corporis odio fuga est veritatis dignissimos obcaecati? Iusto autem praesentium earum quasi ipsa pariatur laboriosam, temporibus quas incidunt? Sed labore repellendus necessitatibus dolore?",
        "quantity": 0,
        "minOrder": 2,
        "price": 12000,
        "shipping": 80,
        "avaiableQuentty": 350,
        "rating": 3,
        "review": "Avarage good with value and quality",
        "status": "Hot",
        "offer": "30",
        "tag": "Pickup",
        "stock": "available"
    },
    {
        "category": "Small",
        "color": "Silver",
        "name": "CURBURETOR",
        "brand": "Lemborgeni",
        "pictures": {
            "img1": "https://i.ibb.co/6YFhMjq/H3846380f8aac4444b29cb9c35add55d3i.jpg",
            "img2": "https://i.ibb.co/jfT91NT/2.jpg",
            "img3": "https://i.ibb.co/mRvg6P0/3.webp",
            "img4": "https://i.ibb.co/12hstgx/4.jpg"
        },
        "description": "Lorem ipsum dolor sit amet consectetur, adipisicing elit. Ex molestias iure eaque vero expedita consequuntur accusamus, perferendis fugit, ut ratione blanditiis veritatis aut, temporibus esse doloremque dicta? Corporis odio fuga est veritatis dignissimos obcaecati? Iusto autem praesentium earum quasi ipsa pariatur laboriosam, temporibus quas incidunt? Sed labore repellendus necessitatibus dolore?",
        "quantity": 0,
        "minOrder": 2,
        "price": 10000,
        "shipping": 80,
        "avaiableQuentty": 350,
        "rating": 3,
        "review": "Avarage good with value and quality",
        "status": "New",
        "offer": "",
        "tag": "Bus",
        "stock": "out"
    },
    {
        "category": "Medium",
        "color": "White",
        "name": "MIRROR",
        "brand": "Acura",
        "pictures": {
            "img1": "https://i.ibb.co/hYr7ZZN/107911583-car-back-and-side-mirrors-isolated-on-white-background-3d-illustration.jpg",
            "img2": "https://i.ibb.co/jfT91NT/2.jpg",
            "img3": "https://i.ibb.co/mRvg6P0/3.webp",
            "img4": "https://i.ibb.co/12hstgx/4.jpg"
        },
        "description": "Lorem ipsum dolor sit amet consectetur, adipisicing elit. Ex molestias iure eaque vero expedita consequuntur accusamus, perferendis fugit, ut ratione blanditiis veritatis aut, temporibus esse doloremque dicta? Corporis odio fuga est veritatis dignissimos obcaecati? Iusto autem praesentium earum quasi ipsa pariatur laboriosam, temporibus quas incidunt? Sed labore repellendus necessitatibus dolore?",
        "quantity": 0,
        "minOrder": 2,
        "price": 8000,
        "shipping": 80,
        "avaiableQuentty": 350,
        "rating": 4,
        "review": "Avarage good with value and quality",
        "status": "",
        "offer": "50",
        "tag": "Car",
        "stock": "available"
    },
    {
        "category": "Large",
        "color": "Black",
        "name": "TIRE",
        "brand": "Alfa Romeo",
        "pictures": {
            "img1": "https://i.ibb.co/hZrG403/Cheap-Tyres-Melbourne-Australia.jpg",
            "img2": "https://i.ibb.co/jfT91NT/2.jpg",
            "img3": "https://i.ibb.co/mRvg6P0/3.webp",
            "img4": "https://i.ibb.co/12hstgx/4.jpg"
        },
        "description": "Lorem ipsum dolor sit amet consectetur, adipisicing elit. Ex molestias iure eaque vero expedita consequuntur accusamus, perferendis fugit, ut ratione blanditiis veritatis aut, temporibus esse doloremque dicta? Corporis odio fuga est veritatis dignissimos obcaecati? Iusto autem praesentium earum quasi ipsa pariatur laboriosam, temporibus quas incidunt? Sed labore repellendus necessitatibus dolore?",
        "quantity": 0,
        "minOrder": 2,
        "price": 6000,
        "shipping": 80,
        "avaiableQuentty": 350,
        "rating": 5,
        "review": "Avarage good with value and quality",
        "status": "New",
        "offer": "",
        "tag": "Truck",
        "stock": "out"
    },
    {
        "category": "Extra-Large",
        "color": "Blue",
        "name": "PISTON",
        "brand": "Bentley",
        "pictures": {
            "img1": "https://i.ibb.co/3vrnHdT/car-piston-500x500.jpg",
            "img2": "https://i.ibb.co/jfT91NT/2.jpg",
            "img3": "https://i.ibb.co/mRvg6P0/3.webp",
            "img4": "https://i.ibb.co/12hstgx/4.jpg"
        },
        "description": "Lorem ipsum dolor sit amet consectetur, adipisicing elit. Ex molestias iure eaque vero expedita consequuntur accusamus, perferendis fugit, ut ratione blanditiis veritatis aut, temporibus esse doloremque dicta? Corporis odio fuga est veritatis dignissimos obcaecati? Iusto autem praesentium earum quasi ipsa pariatur laboriosam, temporibus quas incidunt? Sed labore repellendus necessitatibus dolore?",
        "quantity": 0,
        "minOrder": 2,
        "price": 3000,
        "shipping": 80,
        "avaiableQuentty": 350,
        "rating": 4,
        "review": "Avarage good with value and quality",
        "status": "",
        "offer": "10",
        "tag": "Pickup",
        "stock": "available"
    },
    {
        "category": "Small",
        "color": "Blue",
        "name": "WHEEL",
        "brand": "Buick",
        "pictures": {
            "img1": "https://i.ibb.co/VtRSkKs/download.jpg",
            "img2": "https://i.ibb.co/jfT91NT/2.jpg",
            "img3": "https://i.ibb.co/mRvg6P0/3.webp",
            "img4": "https://i.ibb.co/12hstgx/4.jpg"
        },
        "description": "Lorem ipsum dolor sit amet consectetur, adipisicing elit. Ex molestias iure eaque vero expedita consequuntur accusamus, perferendis fugit, ut ratione blanditiis veritatis aut, temporibus esse doloremque dicta? Corporis odio fuga est veritatis dignissimos obcaecati? Iusto autem praesentium earum quasi ipsa pariatur laboriosam, temporibus quas incidunt? Sed labore repellendus necessitatibus dolore?",
        "quantity": 0,
        "minOrder": 2,
        "price": 4000,
        "shipping": 80,
        "avaiableQuentty": 350,
        "rating": 3,
        "review": "Avarage good with value and quality",
        "status": "Hot",
        "offer": "",
        "tag": "Bus",
        "stock": "out"
    },
    {
        "category": "Extra-Large",
        "color": " Silver",
        "name": "BEEP",
        "brand": "Chevrolet",
        "pictures": {
            "img1": "https://i.ibb.co/f4hm13g/61w6i-Ja-YCXS-AC-SS450.jpg",
            "img2": "https://i.ibb.co/jfT91NT/2.jpg",
            "img3": "https://i.ibb.co/mRvg6P0/3.webp",
            "img4": "https://i.ibb.co/12hstgx/4.jpg"
        },
        "description": "Lorem ipsum dolor sit amet consectetur, adipisicing elit. Ex molestias iure eaque vero expedita consequuntur accusamus, perferendis fugit, ut ratione blanditiis veritatis aut, temporibus esse doloremque dicta? Corporis odio fuga est veritatis dignissimos obcaecati? Iusto autem praesentium earum quasi ipsa pariatur laboriosam, temporibus quas incidunt? Sed labore repellendus necessitatibus dolore?",
        "quantity": 0,
        "minOrder": 2,
        "price": 2000,
        "shipping": 80,
        "avaiableQuentty": 350,
        "rating": 5,
        "review": "Avarage good with value and quality",
        "status": "",
        "offer": "20",
        "tag": "Car",
        "stock": "available"
    },
    {
        "category": "Medium",
        "color": "White",
        "name": "BRAKE SHOE",
        "brand": "Cadillac",
        "pictures": {
            "img1": "https://i.ibb.co/99B08tY/1-click-extreme-z36-truck-and-tow-front-vented-rotors-brake-kit-3.jpg",
            "img2": "https://i.ibb.co/jfT91NT/2.jpg",
            "img3": "https://i.ibb.co/mRvg6P0/3.webp",
            "img4": "https://i.ibb.co/12hstgx/4.jpg"
        },
        "description": "Lorem ipsum dolor sit amet consectetur, adipisicing elit. Ex molestias iure eaque vero expedita consequuntur accusamus, perferendis fugit, ut ratione blanditiis veritatis aut, temporibus esse doloremque dicta? Corporis odio fuga est veritatis dignissimos obcaecati? Iusto autem praesentium earum quasi ipsa pariatur laboriosam, temporibus quas incidunt? Sed labore repellendus necessitatibus dolore?",
        "quantity": 0,
        "minOrder": 2,
        "price": 8000,
        "shipping": 80,
        "avaiableQuentty": 350,
        "rating": 3,
        "review": "Avarage good with value and quality",
        "status": "",
        "offer": "",
        "tag": "Bus",
        "stock": "out"
    },
    {
        "category": "Large",
        "color": "Black",
        "name": "SPEEDMETER",
        "brand": "Honda",
        "pictures": {
            "img1": "https://i.ibb.co/VB3w7JF/images-1.jpg",
            "img2": "https://i.ibb.co/jfT91NT/2.jpg",
            "img3": "https://i.ibb.co/mRvg6P0/3.webp",
            "img4": "https://i.ibb.co/12hstgx/4.jpg"
        },
        "description": "Lorem ipsum dolor sit amet consectetur, adipisicing elit. Ex molestias iure eaque vero expedita consequuntur accusamus, perferendis fugit, ut ratione blanditiis veritatis aut, temporibus esse doloremque dicta? Corporis odio fuga est veritatis dignissimos obcaecati? Iusto autem praesentium earum quasi ipsa pariatur laboriosam, temporibus quas incidunt? Sed labore repellendus necessitatibus dolore?",
        "quantity": 0,
        "minOrder": 2,
        "price": 6000,
        "shipping": 80,
        "avaiableQuentty": 350,
        "rating": 2,
        "review": "Avarage good with value and quality",
        "status": "New",
        "offer": "",
        "tag": "Pickup",
        "stock": "available"
    },
    {
        "category": "Small",
        "color": "Silver",
        "name": "SPARK PLUG",
        "brand": "Audi",
        "pictures": {
            "img1": "https://i.ibb.co/0GxqwS7/Automobile-Parts-Lfr5aix-11-4469-Iridium-IX-Auto-Car-Spark-Plugs.jpg",
            "img2": "https://i.ibb.co/jfT91NT/2.jpg",
            "img3": "https://i.ibb.co/mRvg6P0/3.webp",
            "img4": "https://i.ibb.co/12hstgx/4.jpg"
        },
        "description": "Lorem ipsum dolor sit amet consectetur, adipisicing elit. Ex molestias iure eaque vero expedita consequuntur accusamus, perferendis fugit, ut ratione blanditiis veritatis aut, temporibus esse doloremque dicta? Corporis odio fuga est veritatis dignissimos obcaecati? Iusto autem praesentium earum quasi ipsa pariatur laboriosam, temporibus quas incidunt? Sed labore repellendus necessitatibus dolore?",
        "quantity": 0,
        "minOrder": 2,
        "price": 4000,
        "shipping": 80,
        "avaiableQuentty": 350,
        "rating": 3,
        "review": "Avarage good with value and quality",
        "status": "Hot",
        "offer": "",
        "tag": "Truck",
        "stock": "available"
    },
    {
        "category": "Medium",
        "color": "White",
        "name": "BATTERY",
        "brand": "Ford",
        "pictures": {
            "img1": "https://i.ibb.co/rM2LFbv/istockphoto-899016436-612x612.jpg",
            "img2": "https://i.ibb.co/jfT91NT/2.jpg",
            "img3": "https://i.ibb.co/mRvg6P0/3.webp",
            "img4": "https://i.ibb.co/12hstgx/4.jpg"
        },
        "description": "Lorem ipsum dolor sit amet consectetur, adipisicing elit. Ex molestias iure eaque vero expedita consequuntur accusamus, perferendis fugit, ut ratione blanditiis veritatis aut, temporibus esse doloremque dicta? Corporis odio fuga est veritatis dignissimos obcaecati? Iusto autem praesentium earum quasi ipsa pariatur laboriosam, temporibus quas incidunt? Sed labore repellendus necessitatibus dolore?",
        "quantity": 0,
        "minOrder": 2,
        "price": 12000,
        "shipping": 80,
        "avaiableQuentty": 350,
        "rating": 4,
        "review": "Avarage good with value and quality",
        "status": "",
        "offer": "",
        "tag": "Car",
        "stock": "available"
    },
    {
        "category": "Large",
        "color": "Black",
        "name": "EXHAUST PIPE",
        "brand": "BMW",
        "pictures": {
            "img1": "https://i.ibb.co/wJ5LSDW/157783049-max.jpg",
            "img2": "https://i.ibb.co/jfT91NT/2.jpg",
            "img3": "https://i.ibb.co/mRvg6P0/3.webp",
            "img4": "https://i.ibb.co/12hstgx/4.jpg"
        },
        "description": "Lorem ipsum dolor sit amet consectetur, adipisicing elit. Ex molestias iure eaque vero expedita consequuntur accusamus, perferendis fugit, ut ratione blanditiis veritatis aut, temporibus esse doloremque dicta? Corporis odio fuga est veritatis dignissimos obcaecati? Iusto autem praesentium earum quasi ipsa pariatur laboriosam, temporibus quas incidunt? Sed labore repellendus necessitatibus dolore?",
        "quantity": 0,
        "minOrder": 2,
        "price": 12000,
        "shipping": 80,
        "avaiableQuentty": 350,
        "rating": 4,
        "review": "Avarage good with value and quality",
        "status": "New",
        "offer": "70",
        "tag": "Bus",
        "stock": "available"
    },
    {
        "category": "Extra-Large",
        "color": "Blue",
        "name": "WINDSHIELD",
        "brand": "Audi",
        "pictures": {
            "img1": "https://i.ibb.co/MftdK5q/automotive-car-glass-500x500.jpg",
            "img2": "https://i.ibb.co/jfT91NT/2.jpg",
            "img3": "https://i.ibb.co/mRvg6P0/3.webp",
            "img4": "https://i.ibb.co/12hstgx/4.jpg"
        },
        "description": "Lorem ipsum dolor sit amet consectetur, adipisicing elit. Ex molestias iure eaque vero expedita consequuntur accusamus, perferendis fugit, ut ratione blanditiis veritatis aut, temporibus esse doloremque dicta? Corporis odio fuga est veritatis dignissimos obcaecati? Iusto autem praesentium earum quasi ipsa pariatur laboriosam, temporibus quas incidunt? Sed labore repellendus necessitatibus dolore?",
        "quantity": 0,
        "minOrder": 2,
        "price": 20000,
        "shipping": 80,
        "avaiableQuentty": 350,
        "rating": 3,
        "review": "Avarage good with value and quality",
        "status": "Hot",
        "offer": "30",
        "tag": "Pickup",
        "stock": "available"
    },
    {
        "category": "Small",
        "color": "Silver",
        "name": "CURBURETOR",
        "brand": "Toyota",
        "pictures": {
            "img1": "https://i.ibb.co/6YFhMjq/H3846380f8aac4444b29cb9c35add55d3i.jpg",
            "img2": "https://i.ibb.co/jfT91NT/2.jpg",
            "img3": "https://i.ibb.co/mRvg6P0/3.webp",
            "img4": "https://i.ibb.co/12hstgx/4.jpg"
        },
        "description": "Lorem ipsum dolor sit amet consectetur, adipisicing elit. Ex molestias iure eaque vero expedita consequuntur accusamus, perferendis fugit, ut ratione blanditiis veritatis aut, temporibus esse doloremque dicta? Corporis odio fuga est veritatis dignissimos obcaecati? Iusto autem praesentium earum quasi ipsa pariatur laboriosam, temporibus quas incidunt? Sed labore repellendus necessitatibus dolore?",
        "quantity": 0,
        "minOrder": 2,
        "price": 10000,
        "shipping": 80,
        "avaiableQuentty": 350,
        "rating": 3,
        "review": "Avarage good with value and quality",
        "status": "New",
        "offer": "",
        "tag": "Truck",
        "stock": "available"
    },
    {
        "category": "Medium",
        "color": "White",
        "name": "MIRROR",
        "brand": "BMW",
        "pictures": {
            "img1": "https://i.ibb.co/hYr7ZZN/107911583-car-back-and-side-mirrors-isolated-on-white-background-3d-illustration.jpg",
            "img2": "https://i.ibb.co/jfT91NT/2.jpg",
            "img3": "https://i.ibb.co/mRvg6P0/3.webp",
            "img4": "https://i.ibb.co/12hstgx/4.jpg"
        },
        "description": "Lorem ipsum dolor sit amet consectetur, adipisicing elit. Ex molestias iure eaque vero expedita consequuntur accusamus, perferendis fugit, ut ratione blanditiis veritatis aut, temporibus esse doloremque dicta? Corporis odio fuga est veritatis dignissimos obcaecati? Iusto autem praesentium earum quasi ipsa pariatur laboriosam, temporibus quas incidunt? Sed labore repellendus necessitatibus dolore?",
        "quantity": 0,
        "minOrder": 2,
        "price": 2000,
        "shipping": 80,
        "avaiableQuentty": 350,
        "rating": 4,
        "review": "Avarage good with value and quality",
        "status": "",
        "offer": "50",
        "tag": "Car",
        "stock": "available"
    },
    {
        "category": "Large",
        "color": "Black",
        "name": "TIRE",
        "brand": "Toyota",
        "pictures": {
            "img1": "https://i.ibb.co/hZrG403/Cheap-Tyres-Melbourne-Australia.jpg",
            "img2": "https://i.ibb.co/jfT91NT/2.jpg",
            "img3": "https://i.ibb.co/mRvg6P0/3.webp",
            "img4": "https://i.ibb.co/12hstgx/4.jpg"
        },
        "description": "Lorem ipsum dolor sit amet consectetur, adipisicing elit. Ex molestias iure eaque vero expedita consequuntur accusamus, perferendis fugit, ut ratione blanditiis veritatis aut, temporibus esse doloremque dicta? Corporis odio fuga est veritatis dignissimos obcaecati? Iusto autem praesentium earum quasi ipsa pariatur laboriosam, temporibus quas incidunt? Sed labore repellendus necessitatibus dolore?",
        "quantity": 0,
        "minOrder": 2,
        "price": 3000,
        "shipping": 80,
        "avaiableQuentty": 350,
        "rating": 5,
        "review": "Avarage good with value and quality",
        "status": "New",
        "offer": "",
        "tag": "Bus",
        "stock": "out"
    },
    {
        "category": "Extra-Large",
        "color": "Blue",
        "name": "PISTON",
        "brand": "Audi",
        "pictures": {
            "img1": "https://i.ibb.co/3vrnHdT/car-piston-500x500.jpg",
            "img2": "https://i.ibb.co/jfT91NT/2.jpg",
            "img3": "https://i.ibb.co/mRvg6P0/3.webp",
            "img4": "https://i.ibb.co/12hstgx/4.jpg"
        },
        "description": "Lorem ipsum dolor sit amet consectetur, adipisicing elit. Ex molestias iure eaque vero expedita consequuntur accusamus, perferendis fugit, ut ratione blanditiis veritatis aut, temporibus esse doloremque dicta? Corporis odio fuga est veritatis dignissimos obcaecati? Iusto autem praesentium earum quasi ipsa pariatur laboriosam, temporibus quas incidunt? Sed labore repellendus necessitatibus dolore?",
        "quantity": 0,
        "minOrder": 2,
        "price": 4000,
        "shipping": 80,
        "avaiableQuentty": 350,
        "rating": 4,
        "review": "Avarage good with value and quality",
        "status": "",
        "offer": "10",
        "tag": "Pickup",
        "stock": "available"
    },
    {
        "category": "Small",
        "color": "Mercury Black",
        "name": "WHEEL",
        "brand": "BMW",
        "pictures": {
            "img1": "https://i.ibb.co/VtRSkKs/download.jpg",
            "img2": "https://i.ibb.co/jfT91NT/2.jpg",
            "img3": "https://i.ibb.co/mRvg6P0/3.webp",
            "img4": "https://i.ibb.co/12hstgx/4.jpg"
        },
        "description": "Lorem ipsum dolor sit amet consectetur, adipisicing elit. Ex molestias iure eaque vero expedita consequuntur accusamus, perferendis fugit, ut ratione blanditiis veritatis aut, temporibus esse doloremque dicta? Corporis odio fuga est veritatis dignissimos obcaecati? Iusto autem praesentium earum quasi ipsa pariatur laboriosam, temporibus quas incidunt? Sed labore repellendus necessitatibus dolore?",
        "quantity": 0,
        "minOrder": 2,
        "price": 10000,
        "shipping": 80,
        "avaiableQuentty": 350,
        "rating": 3,
        "review": "Avarage good with value and quality",
        "status": "Hot",
        "offer": "",
        "tag": "Truck",
        "stock": "available"
    },
    {
        "category": "Extra-Large",
        "color": " Red",
        "name": "BEEP",
        "brand": "Audi",
        "pictures": {
            "img1": "https://i.ibb.co/f4hm13g/61w6i-Ja-YCXS-AC-SS450.jpg",
            "img2": "https://i.ibb.co/jfT91NT/2.jpg",
            "img3": "https://i.ibb.co/mRvg6P0/3.webp",
            "img4": "https://i.ibb.co/12hstgx/4.jpg"
        },
        "description": "Lorem ipsum dolor sit amet consectetur, adipisicing elit. Ex molestias iure eaque vero expedita consequuntur accusamus, perferendis fugit, ut ratione blanditiis veritatis aut, temporibus esse doloremque dicta? Corporis odio fuga est veritatis dignissimos obcaecati? Iusto autem praesentium earum quasi ipsa pariatur laboriosam, temporibus quas incidunt? Sed labore repellendus necessitatibus dolore?",
        "quantity": 0,
        "minOrder": 2,
        "price": 8000,
        "shipping": 80,
        "avaiableQuentty": 350,
        "rating": 5,
        "review": "Avarage good with value and quality",
        "status": "",
        "offer": "20",
        "tag": "Car",
        "stock": "available"
    },
    {
        "category": "Medium",
        "color": "Yellow",
        "name": "BRAKE SHOE",
        "brand": "Toyota",
        "pictures": {
            "img1": "https://i.ibb.co/99B08tY/1-click-extreme-z36-truck-and-tow-front-vented-rotors-brake-kit-3.jpg",
            "img2": "https://i.ibb.co/jfT91NT/2.jpg",
            "img3": "https://i.ibb.co/mRvg6P0/3.webp",
            "img4": "https://i.ibb.co/12hstgx/4.jpg"
        },
        "description": "Lorem ipsum dolor sit amet consectetur, adipisicing elit. Ex molestias iure eaque vero expedita consequuntur accusamus, perferendis fugit, ut ratione blanditiis veritatis aut, temporibus esse doloremque dicta? Corporis odio fuga est veritatis dignissimos obcaecati? Iusto autem praesentium earum quasi ipsa pariatur laboriosam, temporibus quas incidunt? Sed labore repellendus necessitatibus dolore?",
        "quantity": 0,
        "minOrder": 2,
        "price": 2000,
        "shipping": 80,
        "avaiableQuentty": 350,
        "rating": 3,
        "review": "Avarage good with value and quality",
        "status": "",
        "offer": "",
        "tag": "Bus",
        "stock": "available"
    },
    {
        "category": "Large",
        "color": "Black",
        "name": "SPEEDMETER",
        "brand": "Hyundai",
        "pictures": {
            "img1": "https://i.ibb.co/VB3w7JF/images-1.jpg",
            "img2": "https://i.ibb.co/jfT91NT/2.jpg",
            "img3": "https://i.ibb.co/mRvg6P0/3.webp",
            "img4": "https://i.ibb.co/12hstgx/4.jpg"
        },
        "description": "Lorem ipsum dolor sit amet consectetur, adipisicing elit. Ex molestias iure eaque vero expedita consequuntur accusamus, perferendis fugit, ut ratione blanditiis veritatis aut, temporibus esse doloremque dicta? Corporis odio fuga est veritatis dignissimos obcaecati? Iusto autem praesentium earum quasi ipsa pariatur laboriosam, temporibus quas incidunt? Sed labore repellendus necessitatibus dolore?",
        "quantity": 0,
        "minOrder": 2,
        "price": 5000,
        "shipping": 80,
        "avaiableQuentty": 350,
        "rating": 2,
        "review": "Avarage good with value and quality",
        "status": "New",
        "offer": "",
        "tag": "Pickup",
        "stock": "available"
    }
]